sqlalchemy_function/__init__.py
sqlalchemy_function/function_mixin.py
sqlalchemy_function/function_relator.py
sqlalchemy_function-0.0.9.dist-info/LICENSE
sqlalchemy_function-0.0.9.dist-info/METADATA
sqlalchemy_function-0.0.9.dist-info/WHEEL
sqlalchemy_function-0.0.9.dist-info/top_level.txt
sqlalchemy_function-0.0.9.dist-info/RECORD
