Metadata-Version: 2.1
Name: sqlalchemy-function
Version: 0.0.9
Summary: Bases and Mixins to store functions for later execution
Home-page: https://dsbowen.github.io/sqlalchemy-function/
Author: Dillon Bowen
Author-email: dsbowen@wharton.upenn.edu
License: UNKNOWN
Platform: UNKNOWN
Classifier: Programming Language :: Python :: 3
Classifier: License :: OSI Approved :: MIT License
Classifier: Operating System :: OS Independent
Requires-Python: >=3.6
Requires-Dist: sqlalchemy (>=1.3.12)
Requires-Dist: sqlalchemy-mutable (>=0.0.8)
